pyplus/__init__.py
pyplus/abstract.py
pyplus/common.py
pyplus/data.py
pyplus/decorators.py
pyplus/json.py
pyplus/object.py
pyplus/parse.py
pyplus/path.py
pyplus/singleton.py
pyplus/string.py
pyplus/table.py
pyplus/temp.py
pyplus-0.1.5.dist-info/DESCRIPTION.rst
pyplus-0.1.5.dist-info/METADATA
pyplus-0.1.5.dist-info/RECORD
pyplus-0.1.5.dist-info/WHEEL
pyplus-0.1.5.dist-info/metadata.json
pyplus-0.1.5.dist-info/top_level.txt
