Metadata-Version: 2.0
Name: pyplus
Version: 0.1.5
Summary: A library containing a collection of python extensions.
Home-page: https://github.com/alexbahnisch/pyplus
Author: Alex Bahnisch
Author-email: alexbahnisch@gmail.com
License: MIT
Keywords: collection extensions plus python
Platform: UNKNOWN
Classifier: Development Status :: 3 - Alpha
Classifier: Intended Audience :: Developers
Classifier: Intended Audience :: Science/Research
Classifier: Natural Language :: English
Classifier: License :: OSI Approved :: MIT License
Classifier: Operating System :: OS Independent
Classifier: Programming Language :: Python :: 3
Classifier: Programming Language :: Python :: 3.5
Classifier: Programming Language :: Python :: 3.6
Classifier: Programming Language :: Python :: Implementation :: CPython
Requires-Python: >=3.5
